openapi_client/__init__.py
openapi_client/api_client.py
openapi_client/configuration.py
openapi_client/exceptions.py
openapi_client/model_utils.py
openapi_client/rest.py
openapi_client/api/__init__.py
openapi_client/api/audience_api.py
openapi_client/api/text_api.py
openapi_client/apis/__init__.py
openapi_client/model/__init__.py
openapi_client/model/inline_object.py
openapi_client/model/inline_object1.py
openapi_client/model/inline_object2.py
openapi_client/model/inline_response200.py
openapi_client/model/inline_response2001.py
openapi_client/model/inline_response2001_response.py
openapi_client/model/inline_response2002.py
openapi_client/model/inline_response2002_response.py
openapi_client/model/inline_response2003.py
openapi_client/model/inline_response200_response.py
openapi_client/model/inline_response200_response_value.py
openapi_client/model/inline_response200_response_value_values.py
openapi_client/model/v1_audience_user_response.py
openapi_client/models/__init__.py
redguy_api-1.0.0.dist-info/METADATA
redguy_api-1.0.0.dist-info/WHEEL
redguy_api-1.0.0.dist-info/top_level.txt
redguy_api-1.0.0.dist-info/RECORD
